mystit/__about__.py
mystit/__init__.py
mystit/errors.py
mystit/frontmatter.py
mystit/myst.py
mystit/plugins/__init__.py
mystit/plugins/admonition.py
mystit/plugins/emoji.py
mystit/plugins/figure.py
mystit/plugins/pygments.py
mystit/plugins/substitutions.py
mystit/signals.py
mystit-0.1.0.dist-info/WHEEL
mystit-0.1.0.dist-info/METADATA
mystit-0.1.0.dist-info/RECORD
